iflow_mcp_pab1it0_chess_mcp/__init__.py
iflow_mcp_pab1it0_chess_mcp/main.py
iflow_mcp_pab1it0_chess_mcp/server.py
iflow_mcp_pab1it0_chess_mcp-0.1.0.dist-info/licenses/LICENSE
iflow_mcp_pab1it0_chess_mcp-0.1.0.dist-info/METADATA
iflow_mcp_pab1it0_chess_mcp-0.1.0.dist-info/WHEEL
iflow_mcp_pab1it0_chess_mcp-0.1.0.dist-info/entry_points.txt
iflow_mcp_pab1it0_chess_mcp-0.1.0.dist-info/top_level.txt
iflow_mcp_pab1it0_chess_mcp-0.1.0.dist-info/RECORD
