Metadata-Version: 2.4
Name: iflow-mcp_pab1it0_chess_mcp
Version: 0.1.0
Summary: MCP server for Chess.com API integration
Requires-Python: >=3.10
License-File: LICENSE
Requires-Dist: mcp[cli]>=1.21.0
Requires-Dist: httpx>=0.28.0
Requires-Dist: python-dotenv>=1.0.0
Requires-Dist: structlog>=23.0.0
Requires-Dist: fastmcp>=2.11.3
Provides-Extra: dev
Requires-Dist: pytest>=7.0.0; extra == "dev"
Requires-Dist: pytest-cov>=4.0.0; extra == "dev"
Requires-Dist: pytest-asyncio>=0.21.0; extra == "dev"
Requires-Dist: pytest-mock>=3.10.0; extra == "dev"
Dynamic: license-file
